flask_dance/__init__.py
flask_dance/utils.py
flask_dance/consumer/__init__.py
flask_dance/consumer/base.py
flask_dance/consumer/oauth1.py
flask_dance/consumer/oauth2.py
flask_dance/consumer/requests.py
flask_dance/consumer/storage/__init__.py
flask_dance/consumer/storage/session.py
flask_dance/consumer/storage/sqla.py
flask_dance/contrib/__init__.py
flask_dance/contrib/atlassian.py
flask_dance/contrib/authentiq.py
flask_dance/contrib/azure.py
flask_dance/contrib/digitalocean.py
flask_dance/contrib/discord.py
flask_dance/contrib/dropbox.py
flask_dance/contrib/facebook.py
flask_dance/contrib/fitbit.py
flask_dance/contrib/github.py
flask_dance/contrib/gitlab.py
flask_dance/contrib/google.py
flask_dance/contrib/heroku.py
flask_dance/contrib/jira.py
flask_dance/contrib/linkedin.py
flask_dance/contrib/meetup.py
flask_dance/contrib/nylas.py
flask_dance/contrib/osm.py
flask_dance/contrib/reddit.py
flask_dance/contrib/salesforce.py
flask_dance/contrib/slack.py
flask_dance/contrib/spotify.py
flask_dance/contrib/strava.py
flask_dance/contrib/twitch.py
flask_dance/contrib/twitter.py
flask_dance/contrib/zoho.py
flask_dance/fixtures/__init__.py
flask_dance/fixtures/pytest.py
Flask_Dance-6.1.1.dist-info/LICENSE
Flask_Dance-6.1.1.dist-info/METADATA
Flask_Dance-6.1.1.dist-info/WHEEL
Flask_Dance-6.1.1.dist-info/entry_points.txt
Flask_Dance-6.1.1.dist-info/top_level.txt
Flask_Dance-6.1.1.dist-info/RECORD
