Metadata-Version: 2.1
Name: Flask-Dance
Version: 6.1.1
Summary: Doing the OAuth dance with style using Flask, requests, and oauthlib
Home-page: https://github.com/singingwolfboy/flask-dance
Author: David Baumgold
Author-email: david@davidbaumgold.com
License: MIT
Platform: UNKNOWN
Classifier: License :: OSI Approved :: MIT License
Classifier: Framework :: Flask
Classifier: Framework :: Pytest
Classifier: Programming Language :: Python
Classifier: Programming Language :: Python :: 3
Classifier: Programming Language :: Python :: 3.7
Classifier: Programming Language :: Python :: 3.8
Classifier: Programming Language :: Python :: 3.9
Classifier: Programming Language :: Python :: 3.10
Requires-Python: >=3.6
License-File: LICENSE
Requires-Dist: requests (>=2.0)
Requires-Dist: oauthlib
Requires-Dist: requests-oauthlib (>=1.0.0)
Requires-Dist: Flask (>=2.0.3)
Requires-Dist: Werkzeug
Requires-Dist: urlobject
Provides-Extra: signals
Requires-Dist: blinker ; extra == 'signals'
Provides-Extra: sqla
Requires-Dist: sqlalchemy (>=1.3.11) ; extra == 'sqla'
